paladin_util/__init__.py
paladin_util/complexrange.py
paladin_util/namespace.py
paladin_util-0.0.1.dist-info/LICENSE
paladin_util-0.0.1.dist-info/METADATA
paladin_util-0.0.1.dist-info/WHEEL
paladin_util-0.0.1.dist-info/top_level.txt
paladin_util-0.0.1.dist-info/RECORD
