Metadata-Version: 2.1
Name: paladin-util
Version: 0.0.1
Summary: A utility collection.
Home-page: https://bitbucket.org/MAX1234/paladin-utils/
Author: Max Steinberg
Author-email: nooneishere@supachat.net
License: UNKNOWN
Platform: UNKNOWN
Classifier: Programming Language :: Python :: 3
Classifier: License :: OSI Approved :: GNU General Public License v3 (GPLv3)
Classifier: Operating System :: OS Independent
